<mvc:View controllerName="pg.md.mdCategory.controller.MainList" 
    xmlns:mvc="sap.ui.core.mvc" 
    xmlns="sap.m" 
    xmlns:f="sap.f" 
    xmlns:form="sap.ui.layout.form" 
    xmlns:layout="sap.ui.layout" 
    xmlns:core="sap.ui.core" 
    xmlns:lib-m="ext.lib.m"
    height="100%">

    <f:DynamicPage id="page"
        headerExpanded="false" 
        toggleHeaderOnTitleClick="true">
        <!-- DynamicPage Title -->
        <f:title>
            <f:DynamicPageTitle>
                <f:heading>
                    <Title text="{i18n>appTitle}" />
                </f:heading>
                <f:snappedContent>
                    <form:SimpleForm id="pageSearchFormS" maxContainerCols="2" editable="true" layout="ResponsiveGridLayout" adjustLabelSpan="false" labelSpanL="4" labelSpanM="4" emptySpanL="0" emptySpanM="0" columnsL="2" columnsM="2">
                        <form:content>
                            <VBox>
                                <Label text="Item Name" labelFor="searchKeyword"></Label>
                                <Input id="searchKeyword" placeholder="Item Name"></Input>
                                <layoutData>
                                    <layout:GridData span="XL2 L3 M6 S12" />
                                </layoutData>
                            </VBox>
                        </form:content>
                    </form:SimpleForm>
                </f:snappedContent>
                <f:actions>
                    <Button id="pageSearchButton" text="Search" type="Emphasized" press=".onPageSearchButtonPress" />
                </f:actions>
                <f:navigationActions>
                    <Button icon="sap-icon://unfavorite" type="Transparent" />
                </f:navigationActions>
            </f:DynamicPageTitle>
        </f:title>
        <!-- DynamicPage Header -->
        <f:header>
            <f:DynamicPageHeader pinnable="true">
            </f:DynamicPageHeader>
        </f:header>
        <f:content>
            <VBox>
                <Table id="mainTable" 
                        sticky="HeaderToolbar,ColumnHeaders" 
                        inset="false" 
                        noDataText="{I18N>/NCM0001}"
                        class="sapFDynamicPageAlignContent" 
                        updateFinished=".onMainTableUpdateFinished"
                        items="{list>/MdCategoryItem}"
                        mode="None"
                        width="auto">
                    <headerToolbar>
                        <OverflowToolbar>
                            <Title text="부품 일반정보" level="H2"/>
                            <ToolbarSpacer/>
                            <Button id="testButton1" text="카테고리ItemCode채번테스트" type="Transparent" press=".callNewCategoryItemCode" />
                            <Button id="testButton2" text="카테고리Code채번테스트" type="Transparent" press=".callNewCategoryCode" />
                            <Button id="testButton3" text="VP매핑Multi테스트" type="Transparent" press=".onMainTableMappMultiProcButtonPress" />
                            <Button id="testButton4" text="VP상태Multi테스트" type="Transparent" press=".onMainTableMultiProcButtonPress" />
                            <Button id="testButton5" text="VP3별Mapping목록조회테스트" type="Transparent" press=".getMdMappingItemViewProcList" />
                            <Button id="testButton6" text="VP3별자재/공급별목록 값저장 테스트" type="Transparent" press=".callMappKeyValueListSave" />
                            <Button id="mainTableAddButton" text="{I18N>/ROW_ADD}" type="Transparent" press=".onMainTableAddButtonPress" />
                            <!-- <Button text="행삭제" type="Transparent" press=".onMainTableDelButtonPress" /> -->
                            <Button id="mainTableSaveButton" text="{I18N>/SAVE}" type="Emphasized" press=".onMainTableSaveButtonPress" />
                            <ToolbarSeparator/>
                            <Button icon="sap-icon://action-settings" press=".onMainTablePersoButtonPressed" >
                                <layoutData>
                                    <OverflowToolbarLayoutData priority="NeverOverflow" />
                                </layoutData>
                            </Button>
                        </OverflowToolbar>
                    </headerToolbar>
                    <columns>
                        <Column minScreenWidth="Tablet" hAlign="Center" mergeDuplicates="false" width="3em" >
                            <Text text="S" />
                        </Column>
                        <Column minScreenWidth="Tablet" hAlign="Center" mergeDuplicates="false" width="12em" >
                            <Text text="Sort" />
                        </Column>
                        <Column minScreenWidth="Tablet" hAlign="Center" mergeDuplicates="false" width="20em" >
                            <Text text="Item Name" />
                        </Column>
                        <Column minScreenWidth="Tablet" hAlign="Center" width="15em">
                            <Text text="Item Desc" />
                        </Column>
                        <Column minScreenWidth="Tablet" hAlign="Center" width="12em" >
                            <Text text="Value Type" />
                        </Column>
                        <Column minScreenWidth="Tablet" hAlign="Center" width="20em" >
                            <Text text="Content" />
                        </Column>
                        <Column minScreenWidth="Tablet" hAlign="Center" width="20em" >
                            <Text text="수정일자" />
                        </Column>
                        <Column minScreenWidth="Tablet" hAlign="Center" width="20em" >
                            <Text text="수정자" />
                        </Column>

                    </columns>
                    <items>
                        <ColumnListItem>
                            <cells>
                                <HBox align="Center">
                                    <Text text="{list>_row_state_}"></Text>
                                </HBox>
                                <HBox align="Center">
                                    <Text text="{list>spmd_character_serial_no}"></Text>
                                </HBox>
                                <HBox>
                                    <Input value="{list>spmd_character_code_name}" ></Input>
                                </HBox>
                                <HBox>
                                    <Input value="{list>spmd_character_desc}" ></Input>
                                </HBox>
                                <HBox>
                                    <Text text="{list>spmd_character_type_code}"></Text>
                                </HBox>
                                <HBox>
                                    <Input value="{list>spmd_category_code}" ></Input>
                                </HBox>
                                <HBox align="Center">
                                    <Text text="{list>system_update_dtm}"></Text>
                                </HBox>
                                <HBox align="Center">
                                    <Text text="{list>update_user_id}"></Text>
                                </HBox>
                            </cells>
                        </ColumnListItem>
                    </items>
                </Table>
            </VBox>
        </f:content>
        <!-- DynamicPage Footer -->
        <f:footer>
        </f:footer>
    </f:DynamicPage>
</mvc:View>
