

<core:FragmentDefinition
	xmlns="sap.ui.comp.valuehelpdialog"
    xmlns:m="sap.m"
	xmlns:core="sap.ui.core"
    xmlns:fb="sap.ui.comp.filterbar"
    >
     <!-- <m:VBox class="sapUiSmallMargin">
        <m:VBox>
            <m:SearchField/>
            <m:layoutData>
                <m:layout:GridData span="XL12 L12 M6 S12" />
            </m:layoutData>
        </m:VBox>
    </m:VBox> -->
	<ValueHelpDialog
        id="valueHelpDialog"
		title="Model"
		ok=".onValueHelpOkPress"
		cancel=".onValueHelpCancelPress"
		afterClose=".onValueHelpAfterClose"
        supportMultiselect="false"
		key="part_number"
		descriptionKey="part_number"
	>
    <filterBar>
			<fb:FilterBar advancedMode="true" search=".onFilterBarSearch"  isRunningInValueHelpDialog="true" fieldGroupIds="listFilterBar">
				<fb:filterGroupItems>
                    <fb:FilterGroupItem
                                groupName="__$INTERNAL$"
                                name="TenantId"
                                label="Tenant ID"
                                visibleInFilterBar="true"
                        >
                        <fb:control>
                            <m:Input
                                    name="tenant_id"
                                    selectedKey="L2101"
                                    showSuggestion="false"
                                    showValueHelp="false"
                                    suggestionItems="{
                                        path: '/Requestors',
                                        sorter: { path: 'email_id' }
                                    }"
                            >
                                <core:Item key="{tenant_id}" text="{tenant_id}" />
                            </m:Input>
                        </fb:control>
					</fb:FilterGroupItem>
                </fb:filterGroupItems>
			</fb:FilterBar>
		</filterBar>
	</ValueHelpDialog>
</core:FragmentDefinition>
